[
  {
    "timestamp": "2025-10-24T15:23:55.065099",
    "action": "sell",
    "symbol": "BTCUSD",
    "price": 110768.9,
    "amount": 0.0,
    "gross_value": 0.0,
    "fee": 0.0,
    "net_value": 0.0,
    "reason": "SELL signal from 1 strategies: sentiment: Sentiment: Keyword match (negative): Swiss Bank Sygnum to Launch Bitcoin-Backed Loan Platform With Multi-Sig Wallet Control",
    "value": 0.0
  },
  {
    "timestamp": "2025-10-24T15:25:24.899381",
    "action": "sell",
    "symbol": "BTCUSD",
    "price": 110768.9,
    "amount": 0.0,
    "gross_value": 0.0,
    "fee": 0.0,
    "net_value": 0.0,
    "reason": "SELL signal from 1 strategies: sentiment: Sentiment: Keyword match (negative): Swiss Bank Sygnum to Launch Bitcoin-Backed Loan Platform With Multi-Sig Wallet Control",
    "value": 0.0
  },
  {
    "timestamp": "2025-10-24T15:27:43.847960",
    "action": "sell",
    "symbol": "BTCUSD",
    "price": 110758.5,
    "amount": 0.0,
    "gross_value": 0.0,
    "fee": 0.0,
    "net_value": 0.0,
    "reason": "SELL signal from 1 strategies: sentiment: Sentiment: Keyword match (negative): The Daily: JPMorgan\u2019s BTC and ETH pledge, Polymarket\u2019s token and airdrop plans, OG bitcoin miner\u2019s 14-year dormancy ends, and more",
    "value": 0.0
  },
  {
    "timestamp": "2025-10-24T15:27:44.442243",
    "action": "buy",
    "symbol": "SOLUSD",
    "price": 193.83,
    "amount": 0.0,
    "gross_value": 0.0,
    "fee": 0.0,
    "net_value": 0.0,
    "reason": "BUY signal from 1 strategies: sentiment: Sentiment: Keyword match (positive): BNB Price Prediction: CZ Welcomes Solana Trading Bot Axiom to BNB Chain, Is a 50% Rally to $1,500 Next?",
    "value": 0.0
  },
  {
    "timestamp": "2025-10-24T15:27:44.630070",
    "action": "buy",
    "symbol": "ADAUSD",
    "price": 0.656895,
    "amount": 0.0,
    "gross_value": 0.0,
    "fee": 0.0,
    "net_value": 0.0,
    "reason": "BUY signal from 1 strategies: volume: Volume: OBV rising (accumulation)",
    "value": 0.0
  },
  {
    "timestamp": "2025-10-24T15:32:45.180610",
    "action": "sell",
    "symbol": "BTCUSD",
    "price": 110691.0,
    "amount": 0.0,
    "gross_value": 0.0,
    "fee": 0.0,
    "net_value": 0.0,
    "reason": "SELL signal from 1 strategies: sentiment: Sentiment: Keyword match (negative): Swiss Bank Sygnum to Launch Bitcoin-Backed Loan Platform With Multi-Sig Wallet Control",
    "value": 0.0
  },
  {
    "timestamp": "2025-10-24T15:37:44.644320",
    "action": "sell",
    "symbol": "BTCUSD",
    "price": 110761.7,
    "amount": 0.0,
    "gross_value": 0.0,
    "fee": 0.0,
    "net_value": 0.0,
    "reason": "SELL signal from 1 strategies: sentiment: Sentiment: Keyword match (negative): Swiss Bank Sygnum to Launch Bitcoin-Backed Loan Platform With Multi-Sig Wallet Control",
    "value": 0.0
  },
  {
    "timestamp": "2025-10-24T15:37:44.750681",
    "action": "buy",
    "symbol": "ETHUSD",
    "price": 3938.46,
    "amount": 0.0,
    "gross_value": 0.0,
    "fee": 0.0,
    "net_value": 0.0,
    "reason": "BUY signal from 1 strategies: sentiment: Sentiment: Keyword match (positive): Ethereum Exchange Withdrawal Activity Surges As Balances Drop To New Lows, ETH\u2019s Rally At Hand?",
    "value": 0.0
  },
  {
    "timestamp": "2025-10-24T15:37:44.973555",
    "action": "buy",
    "symbol": "SHIBUSD",
    "price": 1.02e-05,
    "amount": 0.0,
    "gross_value": 0.0,
    "fee": 0.0,
    "net_value": 0.0,
    "reason": "BUY signal from 1 strategies: technical: Technical: RSI: BUY, Momentum: HOLD",
    "value": 0.0
  },
  {
    "timestamp": "2025-10-24T15:37:45.997845",
    "action": "sell",
    "symbol": "UNIUSD",
    "price": 6.291,
    "amount": 0.0,
    "gross_value": 0.0,
    "fee": 0.0,
    "net_value": 0.0,
    "reason": "SELL signal from 1 strategies: technical: Technical: RSI: SELL, Momentum: HOLD",
    "value": 0.0
  },
  {
    "timestamp": "2025-10-24T15:42:44.575850",
    "action": "sell",
    "symbol": "BTCUSD",
    "price": 110772.0,
    "amount": 0.0,
    "gross_value": 0.0,
    "fee": 0.0,
    "net_value": 0.0,
    "reason": "SELL signal from 1 strategies: sentiment: Sentiment: Keyword match (negative): Swiss Bank Sygnum to Launch Bitcoin-Backed Loan Platform With Multi-Sig Wallet Control",
    "value": 0.0
  },
  {
    "timestamp": "2025-10-24T15:47:45.050444",
    "action": "sell",
    "symbol": "BTCUSD",
    "price": 110877.3,
    "amount": 0.0,
    "gross_value": 0.0,
    "fee": 0.0,
    "net_value": 0.0,
    "reason": "SELL signal from 1 strategies: sentiment: Sentiment: Keyword match (negative): Swiss Bank Sygnum to Launch Bitcoin-Backed Loan Platform With Multi-Sig Wallet Control",
    "value": 0.0
  },
  {
    "timestamp": "2025-10-24T15:47:45.986144",
    "action": "sell",
    "symbol": "UNIUSD",
    "price": 6.287,
    "amount": 0.0,
    "gross_value": 0.0,
    "fee": 0.0,
    "net_value": 0.0,
    "reason": "SELL signal from 1 strategies: technical: Technical: SMA: HOLD, RSI: SELL, Momentum: HOLD",
    "value": 0.0
  },
  {
    "timestamp": "2025-10-24T15:52:43.719786",
    "action": "sell",
    "symbol": "BTCUSD",
    "price": 110817.1,
    "amount": 0.0,
    "gross_value": 0.0,
    "fee": 0.0,
    "net_value": 0.0,
    "reason": "SELL signal from 1 strategies: sentiment: Sentiment: Keyword match (negative): Swiss Bank Sygnum to Launch Bitcoin-Backed Loan Platform With Multi-Sig Wallet Control",
    "value": 0.0
  },
  {
    "timestamp": "2025-10-24T15:57:47.991595",
    "action": "sell",
    "symbol": "BTCUSD",
    "price": 110950.0,
    "amount": 0.0,
    "gross_value": 0.0,
    "fee": 0.0,
    "net_value": 0.0,
    "reason": "SELL signal from 1 strategies: sentiment: Sentiment: Keyword match (negative): Swiss Bank Sygnum to Launch Bitcoin-Backed Loan Platform With Multi-Sig Wallet Control",
    "value": 0.0
  },
  {
    "timestamp": "2025-10-24T15:57:49.230055",
    "action": "sell",
    "symbol": "UNIUSD",
    "price": 6.294,
    "amount": 0.0,
    "gross_value": 0.0,
    "fee": 0.0,
    "net_value": 0.0,
    "reason": "SELL signal from 1 strategies: technical: Technical: SMA: HOLD, RSI: SELL, Momentum: HOLD",
    "value": 0.0
  },
  {
    "timestamp": "2025-10-24T16:02:50.962731",
    "action": "sell",
    "symbol": "BTCUSD",
    "price": 110995.9,
    "amount": 0.0,
    "gross_value": 0.0,
    "fee": 0.0,
    "net_value": 0.0,
    "reason": "SELL signal from 1 strategies: sentiment: Sentiment: Keyword match (negative): Swiss Bank Sygnum to Launch Bitcoin-Backed Loan Platform With Multi-Sig Wallet Control",
    "value": 0.0
  },
  {
    "timestamp": "2025-10-24T16:22:26.794852",
    "action": "buy",
    "symbol": "ETHUSD",
    "price": 3937.0,
    "amount": 0.001524,
    "gross_value": 6.0,
    "fee": 0.02,
    "net_value": 6.02,
    "reason": "BUY signal from 1 strategies: sentiment: Sentiment: The announcement of a significant profit target and high margin indicates strong financial health and potential growth, which could positively impact market sentiment.",
    "value": 6.02
  },
  {
    "timestamp": "2025-10-24T16:22:29.940642",
    "action": "buy",
    "symbol": "BTCUSD",
    "price": 100000.0,
    "amount": 0.01,
    "gross_value": 1000.0,
    "fee": 2.6,
    "net_value": 1002.6,
    "reason": "Test buy signal",
    "value": 1002.6
  },
  {
    "timestamp": "2025-10-24T16:22:29.943514",
    "action": "buy",
    "symbol": "BTCUSD",
    "price": 100000.0,
    "amount": 0.01,
    "gross_value": 1000.0,
    "fee": 2.6,
    "net_value": 1002.6,
    "reason": "Low confidence: BUY signal 0.15",
    "value": 1002.6
  },
  {
    "timestamp": "2025-10-24T16:22:29.953838",
    "action": "buy",
    "symbol": "BTCUSD",
    "price": 100000.0,
    "amount": 0.01,
    "gross_value": 1000.0,
    "fee": 2.6,
    "net_value": 1002.6,
    "reason": "Test",
    "value": 1002.6
  },
  {
    "timestamp": "2025-10-24T16:22:29.961222",
    "action": "sell",
    "symbol": "BTCUSD",
    "price": 100000.0,
    "amount": 0.01,
    "gross_value": 1000.0,
    "fee": 2.6,
    "net_value": 997.4,
    "reason": "Test",
    "value": 997.4
  },
  {
    "timestamp": "2025-10-24T16:26:16.301294",
    "action": "sell",
    "symbol": "BTCUSD",
    "price": 110940.0,
    "amount": 5.4e-05,
    "gross_value": 5.99,
    "fee": 0.02,
    "net_value": 5.98,
    "reason": "SELL signal from 1 strategies: sentiment: Sentiment: Keyword match (negative): Swiss Bank Sygnum to Launch Bitcoin-Backed Loan Platform With Multi-Sig Wallet Control",
    "value": 5.98
  },
  {
    "timestamp": "2025-10-24T16:27:45.311066",
    "action": "sell",
    "symbol": "BTCUSD",
    "price": 110934.0,
    "amount": 5.4e-05,
    "gross_value": 5.99,
    "fee": 0.02,
    "net_value": 5.97,
    "reason": "SELL signal from 1 strategies: sentiment: Sentiment: Keyword match (negative): Swiss Bank Sygnum to Launch Bitcoin-Backed Loan Platform With Multi-Sig Wallet Control",
    "value": 5.97
  }
]